{
  "pid": "HF-OPS-ANALYSIS-0007E-MCP-RULES-FIX",
  "timestamp": "2025-08-25T01:00:00.000Z",
  "meta": {
    "headSha": "9f55adf",
    "policy_version": "2025-08-23",
    "rules_version": "1.0.0"
  },
  "compliance": {
    "TALK_v1_format": false,
    "changeset_limits": false,
    "normalized_error_logging": false,
    "evidence_first": true,
    "adaptive_enforcement": true
  },
  "findings": {
    "lane_b_activation": false,
    "mcp_split_strategy": false,
    "structured_errors": false,
    "stop_guard": false
  },
  "next_steps": [
    "Implement TALK v1 compliance",
    "Split MCP na menšie karty",
    "Add normalized error logging",
    "Activate STOP guard"
  ]
}
